swanspawner/__init__.py
swanspawner/_gpuinfo.py
swanspawner/_version.py
swanspawner/swandockerspawner.py
swanspawner/swankubespawner.py
swanspawner/swanspawner.py
swanspawner/templates/options_form_template.html
swanspawner-1.2.32.dist-info/METADATA
swanspawner-1.2.32.dist-info/WHEEL
swanspawner-1.2.32.dist-info/RECORD
