Metadata-Version: 2.4
Name: swanspawner
Version: 1.2.32
Summary: SWAN JupyterHub spawner
Project-URL: Homepage, https://github.com/swan-cern/jupyterhub-extensions
Project-URL: GitHub, https://github.com/swan-cern/jupyterhub-extensions
Author: SWAN Admins
License-Expression: AGPL-3.0
Keywords: CERN,JupyterHub,SWAN,Spawner
Classifier: Intended Audience :: Developers
Classifier: Intended Audience :: Science/Research
Classifier: Intended Audience :: System Administrators
Classifier: Programming Language :: Python
Classifier: Programming Language :: Python :: 3
Requires-Python: >=3.8
Requires-Dist: dockerspawner==12.1.0
Requires-Dist: jupyterhub
Requires-Dist: jupyterhub-kubespawner==6.1.0
Requires-Dist: psutil
